pySpeakNG/__init__.py
pySpeakNG/langs.json
pySpeakNG/pySpeakNG.py
pySpeakNG/voices.json
pySpeakNG-0.1.2.dist-info/LICENSE.txt
pySpeakNG-0.1.2.dist-info/METADATA
pySpeakNG-0.1.2.dist-info/WHEEL
pySpeakNG-0.1.2.dist-info/top_level.txt
pySpeakNG-0.1.2.dist-info/RECORD
